pymodaq_plugins_stanford_research_systems/__init__.py
pymodaq_plugins_stanford_research_systems/utils.py
pymodaq_plugins_stanford_research_systems/daq_move_plugins/__init__.py
pymodaq_plugins_stanford_research_systems/daq_viewer_plugins/__init__.py
pymodaq_plugins_stanford_research_systems/daq_viewer_plugins/plugins_0D/__init__.py
pymodaq_plugins_stanford_research_systems/daq_viewer_plugins/plugins_0D/daq_0Dviewer_LockInSR830.py
pymodaq_plugins_stanford_research_systems/daq_viewer_plugins/plugins_0D/daq_0Dviewer_LockInSR830Legacy.py
pymodaq_plugins_stanford_research_systems/daq_viewer_plugins/plugins_1D/__init__.py
pymodaq_plugins_stanford_research_systems/daq_viewer_plugins/plugins_1D/daq_1Dviewer_LockInSR830.py
pymodaq_plugins_stanford_research_systems/daq_viewer_plugins/plugins_2D/__init__.py
pymodaq_plugins_stanford_research_systems/daq_viewer_plugins/plugins_ND/__init__.py
pymodaq_plugins_stanford_research_systems/exporters/__init__.py
pymodaq_plugins_stanford_research_systems/extensions/__init__.py
pymodaq_plugins_stanford_research_systems/hardware/__init__.py
pymodaq_plugins_stanford_research_systems/models/PIDModelTemplate.py
pymodaq_plugins_stanford_research_systems/models/__init__.py
pymodaq_plugins_stanford_research_systems/resources/__init__.py
pymodaq_plugins_stanford_research_systems/resources/config_template.toml
pymodaq_plugins_stanford_research_systems/scanners/__init__.py
pymodaq_plugins_stanford_research_systems-1.0.2.dist-info/METADATA
pymodaq_plugins_stanford_research_systems-1.0.2.dist-info/WHEEL
pymodaq_plugins_stanford_research_systems-1.0.2.dist-info/entry_points.txt
pymodaq_plugins_stanford_research_systems-1.0.2.dist-info/licenses/LICENSE
pymodaq_plugins_stanford_research_systems-1.0.2.dist-info/RECORD
